3varMUX/threevarMUX.v
module threevarMUX(
    input a,
    input b,
    input c,
    output out);

    wire [3:0] in;
    wire [1:0] sel;

    assign in = {c,c,1'b0,1'b1};
    assign sel = {a,b};

    four2oneMUX varMUX(in, sel, out);

endmodule

module four2oneMUX(
    input [3:0] in,
    input [1:0] sel,
    output out);

    assign out = in[sel];

endmodule

3varMUX/threevarMUX_tb.v
`timescale 1ns/1ns
`include "threevarMUX.v"

module threevarMUX_tb;

reg A;
reg B;
reg C;

threevarMUX uut(A, B, C, OUT);

initial begin

    $dumpfile("threevarMUX_tb.vcd");
    $dumpvars(0, threevarMUX_tb);

    {A, B, C} = {1'b0, 1'b0, 1'b0}; #20;
    {A, B, C} = {1'b0, 1'b0, 1'b1}; #20;
    {A, B, C} = {1'b0, 1'b1, 1'b0}; #20;
    {A, B, C} = {1'b0, 1'b1, 1'b1}; #20;
    {A, B, C} = {1'b1, 1'b0, 1'b0}; #20;
    {A, B, C} = {1'b1, 1'b0, 1'b1}; #20;
    {A, B, C} = {1'b1, 1'b1, 1'b0}; #20;
    {A, B, C} = {1'b1, 1'b1, 1'b1}; #20;
    
    $display("Test complete");

end

endmodule

3varMUX/threevarMUX_tb.vcd
$date
	Wed Jun  8 02:52:03 2022
$end
$version
	Icarus Verilog
$end
$timescale
	1ns
$end
$scope module threevarMUX_tb $end
$var wire 1 ! OUT $end
$var reg 1 " A $end
$var reg 1 # B $end
$var reg 1 $ C $end
$scope module uut $end
$var wire 1 " a $end
$var wire 1 # b $end
$var wire 1 $ c $end
$var wire 2 % sel [1:0] $end
$var wire 1 ! out $end
$var wire 4 & in [3:0] $end
$scope module varMUX $end
$var wire 4 ' in [3:0] $end
$var wire 2 ( sel [1:0] $end
$var wire 1 ! out $end
$upscope $end
$upscope $end
$upscope $end
$enddefinitions $end
#0
$dumpvars
b0 (
b1 '
b1 &
b0 %
0$
0#
0"
1!
$end
#20
b1101 &
b1101 '
1$
#40
0!
b1 %
b1 (
1#
b1 &
b1 '
0$
#60
b1101 &
b1101 '
1$
#80
1"
0!
b10 %
b10 (
0#
b1 &
b1 '
0$
#100
1!
b1101 &
b1101 '
1$
#120
b11 %
b11 (
1#
0!
b1 &
b1 '
0$
#140
1!
b1101 &
b1101 '
1$
